vercel/sandbox/__init__.py
vercel/sandbox/aio.py
vercel/sandbox/api_client.py
vercel/sandbox/base_client.py
vercel/sandbox/command.py
vercel/sandbox/models.py
vercel/sandbox/sandbox.py
vercel/sandbox/snapshot.py
vercel_sandbox-0.0.4.dist-info/METADATA
vercel_sandbox-0.0.4.dist-info/WHEEL
vercel_sandbox-0.0.4.dist-info/top_level.txt
vercel_sandbox-0.0.4.dist-info/RECORD
