Metadata-Version: 2.4
Name: vercel-sandbox
Version: 0.0.4
Summary: Python SDK for Vercel Sandbox
License: MIT
Requires-Python: >=3.10
Requires-Dist: httpx>=0.27.0
Requires-Dist: pydantic>=2.7.0
Requires-Dist: anyio>=4.0.0
Requires-Dist: python-dotenv
Requires-Dist: vercel>=0.3.7
Provides-Extra: dev
Requires-Dist: ruff>=0.5.0; extra == "dev"
Requires-Dist: pytest>=7.0.0; extra == "dev"
Requires-Dist: pytest-asyncio; extra == "dev"
Requires-Dist: mypy; extra == "dev"
Requires-Dist: build; extra == "dev"
Requires-Dist: twine; extra == "dev"
